{
  "page": 3,
  "vat_result": {
    "words_result": {
      "PurchaserAddress": "",
      "PurchaserBank": "",
      "Password": "",
      "CommodityVehicleType": [],
      "SellerRegisterNum": "91510106050062015W",
      "SellerBank": "",
      "CommodityNum": [
        {
          "row": "1",
          "word": "45.225"
        },
        {
          "row": "2",
          "word": "9.651"
        },
        {
          "row": "3",
          "word": "14.74"
        },
        {
          "row": "4",
          "word": "14.88"
        },
        {
          "row": "5",
          "word": "5.202"
        },
        {
          "row": "6",
          "word": "30.768"
        },
        {
          "row": "7",
          "word": "28.935"
        },
        {
          "row": "8",
          "word": "18.09"
        },
        {
          "row": "9",
          "word": "27.036"
        },
        {
          "row": "10",
          "word": "6.122"
        },
        {
          "row": "11",
          "word": "12.116"
        },
        {
          "row": "12",
          "word": "12.78"
        },
        {
          "row": "13",
          "word": "12.6"
        },
        {
          "row": "14",
          "word": "2.505"
        },
        {
          "row": "15",
          "word": "151.9"
        },
        {
          "row": "16",
          "word": "60.2"
        },
        {
          "row": "17",
          "word": "15.305"
        },
        {
          "row": "18",
          "word": "45.69"
        },
        {
          "row": "19",
          "word": "16.886"
        },
        {
          "row": "20",
          "word": "19.244"
        },
        {
          "row": "21",
          "word": "7.137"
        },
        {
          "row": "22",
          "word": "5.112"
        },
        {
          "row": "23",
          "word": "2.505"
        },
        {
          "row": "24",
          "word": "7.56"
        }
      ],
      "CommodityAmount": [
        {
          "row": "1",
          "word": "132473.23"
        },
        {
          "row": "2",
          "word": "27501.08"
        },
        {
          "row": "3",
          "word": "43437.35"
        },
        {
          "row": "4",
          "word": "43849.91"
        },
        {
          "row": "5",
          "word": "14593.22"
        },
        {
          "row": "6",
          "word": "86313.77"
        },
        {
          "row": "7",
          "word": "82708.01"
        },
        {
          "row": "8",
          "word": "53149.38"
        },
        {
          "row": "9",
          "word": "78954.69"
        },
        {
          "row": "10",
          "word": "17986.76"
        },
        {
          "row": "11",
          "word": "35383.01"
        },
        {
          "row": "12",
          "word": "37774.51"
        },
        {
          "row": "13",
          "word": "35904.42"
        },
        {
          "row": "14",
          "word": "7448.50"
        },
        {
          "row": "15",
          "word": "420749.56"
        },
        {
          "row": "16",
          "word": "169945.13"
        },
        {
          "row": "17",
          "word": "42393.50"
        },
        {
          "row": "18",
          "word": "125748.58"
        },
        {
          "row": "19",
          "word": "48715.36"
        },
        {
          "row": "20",
          "word": "55518.09"
        },
        {
          "row": "21",
          "word": "22232.07"
        },
        {
          "row": "22",
          "word": "15019.33"
        },
        {
          "row": "23",
          "word": "7404.16"
        },
        {
          "row": "24",
          "word": "21408.85"
        }
      ],
      "InvoiceType": "电子发票(专用发票)",
      "AmountInWords": "",
      "TotalTax": "849869.60",
      "MachineCode": "",
      "City": "",
      "InvoiceNumDigit": "",
      "Checker": "",
      "InvoiceCode": "",
      "SellerAddress": "",
      "CommodityPrice": [
        {
          "row": "1",
          "word": "2929.2035398230087"
        },
        {
          "row": "2",
          "word": "2849.5575221238937"
        },
        {
          "row": "3",
          "word": "2946.9026548672564"
        },
        {
          "row": "4",
          "word": "2946.9026548672564"
        },
        {
          "row": "5",
          "word": "2805.309734513274"
        },
        {
          "row": "6",
          "word": "2805.309734513274"
        },
        {
          "row": "7",
          "word": "2858.407079646018"
        },
        {
          "row": "8",
          "word": "2938.0530973451328"
        },
        {
          "row": "9",
          "word": "2920.353982300885"
        },
        {
          "row": "10",
          "word": "2938.0530973451328"
        },
        {
          "row": "11",
          "word": "2920.353982300885"
        },
        {
          "row": "12",
          "word": "2955.7522123893805"
        },
        {
          "row": "13",
          "word": "2849.5575221238937"
        },
        {
          "row": "14",
          "word": "2973.451327433628"
        },
        {
          "row": "15",
          "word": "2769.9115044247787"
        },
        {
          "row": "16",
          "word": "2823.008849557522"
        },
        {
          "row": "17",
          "word": "2769.9115044247787"
        },
        {
          "row": "18",
          "word": "2752.212389380531"
        },
        {
          "row": "19",
          "word": "2884.9557522123896"
        },
        {
          "row": "20",
          "word": "2884.9557522123896"
        },
        {
          "row": "21",
          "word": "3115.0442477876104"
        },
        {
          "row": "22",
          "word": "2938.0530973451328"
        },
        {
          "row": "23",
          "word": "2955.7522123893805"
        },
        {
          "row": "24",
          "word": "2831.858407079646"
        }
      ],
      "NoteDrawer": "赵艳红",
      "Province": "",
      "InvoiceNum": "25512000000289128032",
      "CommodityTaxRate": [
        {
          "row": "1",
          "word": "13%"
        },
        {
          "row": "2",
          "word": "13%"
        },
        {
          "row": "3",
          "word": "13%"
        },
        {
          "row": "4",
          "word": "13%"
        },
        {
          "row": "5",
          "word": "13%"
        },
        {
          "row": "6",
          "word": "13%"
        },
        {
          "row": "7",
          "word": "13%"
        },
        {
          "row": "8",
          "word": "13%"
        },
        {
          "row": "9",
          "word": "13%"
        },
        {
          "row": "10",
          "word": "13%"
        },
        {
          "row": "11",
          "word": "13%"
        },
        {
          "row": "12",
          "word": "13%"
        },
        {
          "row": "13",
          "word": "13%"
        },
        {
          "row": "14",
          "word": "13%"
        },
        {
          "row": "15",
          "word": "13%"
        },
        {
          "row": "16",
          "word": "13%"
        },
        {
          "row": "17",
          "word": "13%"
        },
        {
          "row": "18",
          "word": "13%"
        },
        {
          "row": "19",
          "word": "13%"
        },
        {
          "row": "20",
          "word": "13%"
        },
        {
          "row": "21",
          "word": "13%"
        },
        {
          "row": "22",
          "word": "13%"
        },
        {
          "row": "23",
          "word": "13%"
        },
        {
          "row": "24",
          "word": "13%"
        }
      ],
      "ServiceType": "其他",
      "InvoiceDate": "2025年11月28日",
      "CommodityEndDate": [],
      "PurchaserRegisterNum": "91510105MA6DDW761G",
      "CommodityStartDate": [],
      "TotalAmount": "6537458.09",
      "SheetNum": "",
      "CommodityPlateNum": [],
      "PurchaserName": "四川省商投建筑工程有限责任公司",
      "SellerName": "中铁物贸集团有限公司成都分公司",
      "InvoiceNumConfirm": "25512000000289128032",
      "Agent": "否",
      "InvoiceTag": "其他",
      "CommodityUnit": [
        {
          "row": "1",
          "word": "吨"
        },
        {
          "row": "2",
          "word": "吨"
        },
        {
          "row": "3",
          "word": "吨"
        },
        {
          "row": "4",
          "word": "吨"
        },
        {
          "row": "5",
          "word": "吨"
        },
        {
          "row": "6",
          "word": "吨"
        },
        {
          "row": "7",
          "word": "吨"
        },
        {
          "row": "8",
          "word": "吨"
        },
        {
          "row": "9",
          "word": "吨"
        },
        {
          "row": "10",
          "word": "吨"
        },
        {
          "row": "11",
          "word": "吨"
        },
        {
          "row": "12",
          "word": "吨"
        },
        {
          "row": "13",
          "word": "吨"
        },
        {
          "row": "14",
          "word": "吨"
        },
        {
          "row": "15",
          "word": "吨"
        },
        {
          "row": "16",
          "word": "吨"
        },
        {
          "row": "17",
          "word": "吨"
        },
        {
          "row": "18",
          "word": "吨"
        },
        {
          "row": "19",
          "word": "吨"
        },
        {
          "row": "20",
          "word": "吨"
        },
        {
          "row": "21",
          "word": "吨"
        },
        {
          "row": "22",
          "word": "吨"
        },
        {
          "row": "23",
          "word": "吨"
        },
        {
          "row": "24",
          "word": "吨"
        }
      ],
      "CheckCode": "",
      "InvoiceTypeOrg": "电子发票(增值税专用发票)",
      "Remarks": "",
      "Payee": "",
      "CommodityTax": [
        {
          "row": "1",
          "word": "17221.52"
        },
        {
          "row": "2",
          "word": "3575.14"
        },
        {
          "row": "3",
          "word": "5646.85"
        },
        {
          "row": "4",
          "word": "5700.49"
        },
        {
          "row": "5",
          "word": "1897.12"
        },
        {
          "row": "6",
          "word": "11220.79"
        },
        {
          "row": "7",
          "word": "10752.04"
        },
        {
          "row": "8",
          "word": "6909.42"
        },
        {
          "row": "9",
          "word": "10264.11"
        },
        {
          "row": "10",
          "word": "2338.28"
        },
        {
          "row": "11",
          "word": "4599.79"
        },
        {
          "row": "12",
          "word": "4910.69"
        },
        {
          "row": "13",
          "word": "4667.58"
        },
        {
          "row": "14",
          "word": "968.30"
        },
        {
          "row": "15",
          "word": "54697.44"
        },
        {
          "row": "16",
          "word": "22092.87"
        },
        {
          "row": "17",
          "word": "5511.15"
        },
        {
          "row": "18",
          "word": "16347.32"
        },
        {
          "row": "19",
          "word": "6333.00"
        },
        {
          "row": "20",
          "word": "7217.35"
        },
        {
          "row": "21",
          "word": "2890.17"
        },
        {
          "row": "22",
          "word": "1952.51"
        },
        {
          "row": "23",
          "word": "962.54"
        },
        {
          "row": "24",
          "word": "2783.15"
        }
      ],
      "AmountInFiguers": "7387327.69",
      "CommodityName": [
        {
          "row": "1",
          "word": "*黑色金属冶炼压延品*螺纹钢"
        },
        {
          "row": "2",
          "word": "*黑色金属冶炼压延品*盘螺"
        },
        {
          "row": "3",
          "word": "*黑色金属冶炼压延品*盘螺"
        },
        {
          "row": "4",
          "word": "*黑色金属冶炼压延品*盘螺"
        },
        {
          "row": "5",
          "word": "*黑色金属冶炼压延品*螺纹钢"
        },
        {
          "row": "6",
          "word": "*黑色金属冶炼压延品*螺纹钢"
        },
        {
          "row": "7",
          "word": "*黑色金属冶炼压延品*盘螺"
        },
        {
          "row": "8",
          "word": "*黑色金属冶炼压延品*螺纹钢"
        },
        {
          "row": "9",
          "word": "*黑色金属冶炼压延品*螺纹钢"
        },
        {
          "row": "10",
          "word": "*黑色金属冶炼压延品*螺纹钢"
        },
        {
          "row": "11",
          "word": "*黑色金属冶炼压延品*螺纹钢"
        },
        {
          "row": "12",
          "word": "*黑色金属冶炼压延品*螺纹钢"
        },
        {
          "row": "13",
          "word": "*黑色金属冶炼压延品*螺纹钢"
        },
        {
          "row": "14",
          "word": "*黑色金属冶炼压延品*螺纹钢"
        },
        {
          "row": "15",
          "word": "*黑色金属冶炼压延品*螺纹钢"
        },
        {
          "row": "16",
          "word": "*黑色金属冶炼压延品*螺纹钢"
        },
        {
          "row": "17",
          "word": "*黑色金属冶炼压延品*螺纹钢"
        },
        {
          "row": "18",
          "word": "*黑色金属冶炼压延品*螺纹钢"
        },
        {
          "row": "19",
          "word": "*黑色金属冶炼压延品*盘螺"
        },
        {
          "row": "20",
          "word": "*黑色金属冶炼压延品*盘螺"
        },
        {
          "row": "21",
          "word": "*黑色金属冶炼压延品*高线"
        },
        {
          "row": "22",
          "word": "*黑色金属冶炼压延品*螺纹钢"
        },
        {
          "row": "23",
          "word": "*黑色金属冶炼压延品*螺纹钢"
        },
        {
          "row": "24",
          "word": "*黑色金属冶炼压延品*螺"
        }
      ],
      "CommodityType": [
        {
          "row": "1",
          "word": "热轧HRB500E25mm"
        },
        {
          "row": "2",
          "word": "热轧HRB400E10mm"
        },
        {
          "row": "3",
          "word": "热轧HRB400E8mm"
        },
        {
          "row": "4",
          "word": "热轧HRB400E10mm"
        },
        {
          "row": "5",
          "word": "热轧HRB400E20mm"
        },
        {
          "row": "6",
          "word": "热轧HRB400E25mm"
        },
        {
          "row": "7",
          "word": "热轧HRB400E8mm"
        },
        {
          "row": "8",
          "word": "热轧HRB500E25mm"
        },
        {
          "row": "9",
          "word": "热轧HRB500E22mm"
        },
        {
          "row": "10",
          "word": "热轧HRB500E12mm"
        },
        {
          "row": "11",
          "word": "热轧HRB500E16mm"
        },
        {
          "row": "12",
          "word": "热轧HRB500E20mm"
        },
        {
          "row": "13",
          "word": "热轧HRB500E18mm"
        },
        {
          "row": "14",
          "word": "热轧HRB500E14mm"
        },
        {
          "row": "15",
          "word": "热轧HRB400E14mm"
        },
        {
          "row": "16",
          "word": "热轧HRB400E32mm"
        },
        {
          "row": "17",
          "word": "热轧HRB400E12mm"
        },
        {
          "row": "18",
          "word": "热轧HRB400E20mm"
        },
        {
          "row": "19",
          "word": "热轧HRB400E10mm"
        },
        {
          "row": "20",
          "word": "热轧HRB400E8mm"
        },
        {
          "row": "21",
          "word": "热轧HPB3006mm"
        },
        {
          "row": "22",
          "word": "热轧HRB500E20mm"
        },
        {
          "row": "23",
          "word": "热轧HRB500E14mm"
        },
        {
          "row": "24",
          "word": "热轧HRB500E"
        }
      ],
      "OnlinePay": "",
      "PassengerName": [],
      "PassengerIdNum": [],
      "PassengerDate": [],
      "PassengerDeparture": [],
      "PassengerArrival": [],
      "PassengerClass": [],
      "PassengerVehicleType": [],
      "TransportType": [],
      "TransportPlateNum": [],
      "TransportDeparture": [],
      "TransportArrival": [],
      "TransportCargoInfo": []
    },
    "words_result_num": 61,
    "log_id": 2019255503231496074
  }
}